rimmist/__init__.py
rimmist/feature.py
rimmist/utils.py
rimmist-24.5.18.dist-info/LICENSE
rimmist-24.5.18.dist-info/METADATA
rimmist-24.5.18.dist-info/WHEEL
rimmist-24.5.18.dist-info/top_level.txt
rimmist-24.5.18.dist-info/RECORD
